pyargwriter/__init__.py
pyargwriter/__main__.py
pyargwriter/_core/__init__.py
pyargwriter/_core/code_abstracts.py
pyargwriter/_core/code_generator.py
pyargwriter/_core/code_inspector.py
pyargwriter/_core/docstring_parser.py
pyargwriter/_core/structures.py
pyargwriter/api/__init__.py
pyargwriter/api/hydra_plugin.py
pyargwriter/decorator/README.md
pyargwriter/decorator/__init__.py
pyargwriter/decorator/decorator.py
pyargwriter/entrypoint.py
pyargwriter/main.py
pyargwriter/utils/__init__.py
pyargwriter/utils/casts.py
pyargwriter/utils/file_system.py
pyargwriter/utils/formatter.py
pyargwriter/utils/log_level.py
pyargwriter/utils/parser.py
pyargwriter/utils/type_testing.py
pyargwriter-1.1.5.dist-info/METADATA
pyargwriter-1.1.5.dist-info/WHEEL
pyargwriter-1.1.5.dist-info/entry_points.txt
pyargwriter-1.1.5.dist-info/licenses/LICENSE
pyargwriter-1.1.5.dist-info/RECORD
