Metadata-Version: 2.4
Name: pyargwriter
Version: 1.1.5
Summary: Automatically generates ArgumentParser setups for Python classes and their methods.
License: MIT
License-File: LICENSE
Keywords: python,code-generation,ArgumentParser,tooling,argument-parser,documentation-tool,python3
Author: Robin Uhrich
Author-email: robin.uhrich@gmail.com
Requires-Python: >=3.10,<4.0
Classifier: License :: OSI Approved :: MIT License
Classifier: Programming Language :: Python :: 3
Classifier: Programming Language :: Python :: 3.10
Classifier: Programming Language :: Python :: 3.11
Classifier: Programming Language :: Python :: 3.12
Classifier: Programming Language :: Python :: 3.13
Classifier: Programming Language :: Python :: 3.14
Requires-Dist: argparse (>=1.4.0,<2.0.0)
Requires-Dist: black (>=23.12.1,<24.0.0)
Requires-Dist: hydra-core (>=1.3.2,<2.0.0)
Requires-Dist: pyaml (>=23.12.0,<24.0.0)
Project-URL: Repository, https://github.com/RobinU434/PyArgWriter
